fluxgen/__init__.py
fluxgen/template.py
fluxgen/utils.py
fluxgen/client/__init__.py
fluxgen/client/create.py
fluxgen/client/install.py
fluxgen/command/__init__.py
fluxgen/command/create.py
fluxgen/command/install.py
fluxgen/logger/__init__.py
fluxgen/logger/generate.py
fluxgen/logger/logger.py
fluxgen/templates/install-flux.sh
fluxgen/templates/includes/ensure-curve-certificate.sh
fluxgen/templates/includes/install-micromamba.sh
fluxgen/templates/includes/install-munge.sh
fluxgen/templates/includes/write-parse-links-py.sh
fluxgen-0.0.16.dist-info/LICENSE
fluxgen-0.0.16.dist-info/METADATA
fluxgen-0.0.16.dist-info/NOTICE
fluxgen-0.0.16.dist-info/WHEEL
fluxgen-0.0.16.dist-info/entry_points.txt
fluxgen-0.0.16.dist-info/top_level.txt
fluxgen-0.0.16.dist-info/RECORD
