Metadata-Version: 2.1
Name: fluxgen
Version: 0.0.16
Summary: Helper tool to install and configure Flux Framework
Home-page: https://github.com/converged-computing/fluxgen
Author: Vanessasaurus
Author-email: vsoch@users.noreply.github.com
Maintainer: Vanessasaurus
License: MIT
Keywords: multi-cluster,scheduler
Classifier: Intended Audience :: Science/Research
Classifier: Intended Audience :: Developers
Classifier: License :: OSI Approved :: Apache Software License
Classifier: Programming Language :: C
Classifier: Programming Language :: Python
Classifier: Topic :: Software Development
Classifier: Topic :: Scientific/Engineering
Classifier: Operating System :: Unix
Classifier: Programming Language :: Python :: 3.11
License-File: LICENSE
License-File: NOTICE
Requires-Dist: Jinja2
Requires-Dist: pyyaml
